pydmart/__init__.py
pydmart/consts.py
pydmart/enums.py
pydmart/models.py
pydmart/py.typed
pydmart/service.py
pydmart-2.0.0.dist-info/licenses/LICENSE.txt
pydmart-2.0.0.dist-info/METADATA
pydmart-2.0.0.dist-info/WHEEL
pydmart-2.0.0.dist-info/top_level.txt
pydmart-2.0.0.dist-info/RECORD
