Metadata-Version: 2.4
Name: pydmart
Version: 2.0.0
Summary: A client to connect to a Dmart isntance
Home-page: https://github.com/edraj/pydmart
Author: <Kefah Issa>
Author-email: kefah.issa@gmail.com
Classifier: Programming Language :: Python :: 3
Classifier: License :: OSI Approved :: MIT License
Classifier: Operating System :: OS Independent
License-File: LICENSE.txt
Dynamic: license-file
